parameterized_mortgage/__init__.py
parameterized_mortgage/__main__.py
parameterized_mortgage/calculate.py
parameterized_mortgage/dashboard/__init__.py
parameterized_mortgage/dashboard/components.py
parameterized_mortgage/dashboard/panel_dashboard.py
parameterized_mortgage/models/__init__.py
parameterized_mortgage/models/mortgage.py
parameterized_mortgage-0.1.5.dist-info/LICENSE
parameterized_mortgage-0.1.5.dist-info/METADATA
parameterized_mortgage-0.1.5.dist-info/WHEEL
parameterized_mortgage-0.1.5.dist-info/entry_points.txt
parameterized_mortgage-0.1.5.dist-info/RECORD
