Metadata-Version: 2.1
Name: parameterized-mortgage
Version: 0.1.5
Summary: A simple python package to provide mortgage repayment calculations using the French method of amortization
License: GNU V3
Author: Jonathan Mair
Author-email: jonathan.mair@gmail.com
Requires-Python: >=3.10,<4.0
Classifier: License :: Other/Proprietary License
Classifier: Programming Language :: Python :: 3
Classifier: Programming Language :: Python :: 3.10
Classifier: Programming Language :: Python :: 3.11
Requires-Dist: hvplot (>=0.8.4,<0.9.0)
Requires-Dist: matplotlib (>=3.7.2,<4.0.0)
Requires-Dist: pandas (>=2.0.3,<3.0.0)
Requires-Dist: panel (>=1.2.0,<2.0.0)
Requires-Dist: param (>=1.13.0,<2.0.0)
Requires-Dist: plotly (>=5.16.1,<6.0.0)
